Metadata-Version: 1.0
Name: glosm
Version: 0.4.0
Summary: glorified secrets manager
Home-page: UNKNOWN
Author: tutti
Author-email: data@tutti.ch
License: Proprietary
Platform: UNKNOWN
